moveread/ocr/__init__.py
moveread/ocr/__init__.pyi
moveread/ocr/data.py
moveread/ocr/model.py
moveread/ocr/postprocess.py
moveread/ocr/serving.py
moveread/ocr/steps.py
moveread/ocr/cli/__init__.py
moveread/ocr/cli/__init__.pyi
moveread/ocr/cli/_predict.py
moveread/ocr/cli/eval.py
moveread/ocr/cli/export.py
moveread/ocr/cli/main.py
moveread/ocr/cli/serving.py
moveread/ocr/finetuning/__init__.py
moveread/ocr/finetuning/__init__.pyi
moveread/ocr/finetuning/_loop.py
moveread/ocr/finetuning/main.py
moveread/ocr/records/__init__.py
moveread/ocr/records/__init__.pyi
moveread/ocr/records/data.py
moveread/ocr/records/schema.py
moveread_ocr-0.1.25.dist-info/METADATA
moveread_ocr-0.1.25.dist-info/WHEEL
moveread_ocr-0.1.25.dist-info/entry_points.txt
moveread_ocr-0.1.25.dist-info/top_level.txt
moveread_ocr-0.1.25.dist-info/RECORD
