Metadata-Version: 2.1
Name: moveread-ocr
Version: 0.1.25
Summary: Moveread OCR model, in tensorflow
Author-email: Marcel Claramunt <marcel@moveread.com>
Project-URL: repo, https://github.com/moveread/moveread-ocr.git
Requires-Python: >=3.10
Requires-Dist: tensorflow
Requires-Dist: keras
Requires-Dist: jaxtyping
Requires-Dist: haskellian
Requires-Dist: tf-ctc
Requires-Dist: demetric
Requires-Dist: checkptr
Requires-Dist: tensorflow-records
Requires-Dist: tf-tools
Provides-Extra: cli
Requires-Dist: typer; extra == "cli"
Requires-Dist: orjson; extra == "cli"
Requires-Dist: ocr-dataset; extra == "cli"
Requires-Dist: files-dataset; extra == "cli"
